[
  {
    "cartId": 1,
    "name": "Автомат Cyma АК Magpul custom Sport Series BK CM680C",
    "quantity": 1,
    "quantityMax": 100,
    "price": 15030,
    "priceOld": 23530,
    "img": "./content/position-1.png"
  },
  {
    "cartId": 2,
    "name": "Автомат Cyma АК Magpul custom Sport Series BK CM680C",
    "quantity": 1,
    "quantityMax": 100,
    "price": 15030,
    "priceOld": 23530,
    "img": "./content/position-1.png"
  },
  {
    "cartId": 3,
    "name": "Пистолет WE Big Bird Semi GGBB",
    "quantity": 3,
    "quantityMax": 5,
    "price": 20000,
    "priceOld": 20000,
    "img": "./content/position-1.png"
  }
]
